ibr/__init__.py
ibr/_version.py
ibr/efficiency.py
ibr/indebtedness.py
ibr/profitability.py
ibr/reader.py
ibr/utils.py
ibr/valuation.py
pyibr-0.1.1.dist-info/LICENSE
pyibr-0.1.1.dist-info/METADATA
pyibr-0.1.1.dist-info/WHEEL
pyibr-0.1.1.dist-info/top_level.txt
pyibr-0.1.1.dist-info/RECORD
