Metadata-Version: 2.1
Name: pyibr
Version: 0.1.1
Summary: Calculates fundamental analysis indicators of Brazilian companies
Home-page: https://github.com/glourencoffee/pyibr/
Author: Giovanni Lourenço
Author-email: gvnl.developer@outlook.com
License: MIT
Keywords: investment,finances
Requires-Python: >=3.7
License-File: LICENSE
Requires-Dist: pycvm (>=0.3.2)
Requires-Dist: pybov (>=0.1.1)
Requires-Dist: yfinance
